autorefine/__init__.py
autorefine/__main__.py
autorefine/fixes/__init__.py
autorefine/fixes/lint/__init__.py
autorefine/fixes/modernize/__init__.py
autorefine/fixes/modernize/use_raw_super.py
autorefine/fixes/optional/__init__.py
autorefine/fixes/optional/use_more_itertools.py
autorefine/fixes/refactor/__init__.py
autorefine/fixes/refactor/use_dict_fromkeys.py
autorefine/fixes/refactor/use_format_minilanguage.py
autorefine/fixes/refactor/use_keyword_bool_defaults.py
autorefine/fixes/refactor/use_logger_exception.py
autorefine/fixes/refactor/use_pathlib.py
autorefine/fixes/refactor/use_type_aliases.py
autorefine/fixes/refactor/use_typed_namedtuples.py
autorefine/fixes/typing/__init__.py
autorefine/fixes/typing/generate_types.py
autorefine/fixes/typing/postpone_annotations.py
autorefine/fixes/typing/use_builtin_classes.py
autorefine/planning/__init__.py
autorefine/planning/lint/__init__.py
autorefine/planning/refactor/__init__.py
autorefine/planning/typing/__init__.py
autorefine/py.typed
autorefine/tooling/__init__.py
autorefine/tooling/fixit.py
autorefine/tooling/monkeytype.py
autorefine/tooling/ruff.py
autorefine-0.0.1.dist-info/LICENSE
autorefine-0.0.1.dist-info/METADATA
autorefine-0.0.1.dist-info/WHEEL
autorefine-0.0.1.dist-info/RECORD
