Metadata-Version: 2.1
Name: autorefine
Version: 0.0.1
Summary: Mechanize the refactoring process to operate on a large scale.
Home-page: https://github.com/bswck/autorefine
License: GPL-3.0
Author: bswck
Author-email: bswck.dev@gmail.com
Requires-Python: >=3.8,<4.0
Classifier: License :: OSI Approved :: GNU General Public License v3 (GPLv3)
Classifier: Programming Language :: Python :: 3
Classifier: Programming Language :: Python :: 3.8
Classifier: Programming Language :: Python :: 3.9
Classifier: Programming Language :: Python :: 3.10
Classifier: Programming Language :: Python :: 3.11
Classifier: Programming Language :: Python :: 3.12
Project-URL: Coverage, https://coverage-badge.samuelcolvin.workers.dev/redirect/bswck/autorefine
Project-URL: Documentation, https://autorefine.readthedocs.io/en/latest/
Project-URL: Distribution, https://pypi.org/project/autorefine/
Project-URL: Issues, https://github.com/bswck/autorefine/issues
